application_download/__init__.py
application_download/applications-schema.json
application_download/applications.yaml
application_download/applications_definition.py
application_download/cli.py
application_download/py.typed
application_download/versions.yaml
application_download-0.0.1.dev3.dist-info/LICENSE
application_download-0.0.1.dev3.dist-info/METADATA
application_download-0.0.1.dev3.dist-info/WHEEL
application_download-0.0.1.dev3.dist-info/entry_points.txt
application_download-0.0.1.dev3.dist-info/RECORD
